threadpoolctl.py
threadpoolctl-2.2.0.dist-info/LICENSE
threadpoolctl-2.2.0.dist-info/WHEEL
threadpoolctl-2.2.0.dist-info/METADATA
threadpoolctl-2.2.0.dist-info/RECORD
